[{"src":"http://imglf1.ph.126.net/wypSByNGDlgKh7EMOHpERg==/6619294195189057183.jpg","title":"来源：Gaga","date":"2015-01-05","cmt":"","hot":"25"},{"src":"http://imglf1.ph.126.net/vq4Tpr1e2ioRU2DmVWhvWQ==/983755043621216686.jpg","title":"火热来源：乐若鱼","date":"2015-01-05","cmt":"","hot":"25"},{"src":"http://imglf0.ph.126.net/ZwofScLg2-Qx1h8OLawzQQ==/982629143714323839.jpg","title":"来源：抠脚素人渔夫","date":"2015-01-05","cmt":"","hot":"281"},{"src":"http://imglf1.ph.126.net/7YxPq8s6SZySc0yv1lUTSQ==/1058064437472838504.jpg","title":"来源：OSMANTHUS","date":"2015-01-05","cmt":"","hot":"176"},{"src":"http://imglf0.ph.126.net/fI6-ASSvx-NAyTIaO_sguw==/6619499803863451362.jpg","title":"来源：彷徨的青春","date":"2015-01-05","cmt":"","hot":"52"},{"src":"http://imglf1.ph.126.net/tPp37iASjTofs7UCGA0pwA==/2452491472097421532.jpg","title":"来源：OSMANTHUS","date":"2015-01-05","cmt":"","hot":"214"},{"src":"http://imglf0.ph.126.net/cLXsIV9om61KY1DO_pq03w==/1063693937006901633.jpg","title":"来源：飞扬zz_dri","date":"2015-01-02","cmt":"","hot":"38"},{"src":"http://imglf1.ph.126.net/dXqnejx5cfCLCQlpQhKC4A==/3358559422212583459.jpg","title":"性感来源：汉华eric","date":"2015-01-02","cmt":"","hot":"20"},{"src":"http://imglf1.ph.126.net/GUQ5ct0Y0UT6PIq81ihS5w==/6608621235818337247.jpg","title":"来源：马列尼玛逼","date":"2015-01-02","cmt":"","hot":"22"},{"src":"http://imglf0.ph.126.net/UiOuB1f7fGU3SbX2gvHshg==/6608575056329970273.jpg","title":"来源：马列尼玛逼","date":"2015-01-02","cmt":"","hot":"17"}]