[{"src":"http://imglf1.ph.126.net/gT-OunjJ-j2J6NtAwXMSww==/1601874092560657150.jpg","title":"不管是和谁约会见面，约定的时间之前一定要到达。 相关链接：林志颖删林心如微博无水印高清美女图片 腾讯微博首页","date":"2014-01-20","cmt":"","hot":"7"},{"src":"http://imglf0.ph.126.net/Zh85ZfctPrVL5JzWImh_TQ==/1469580853506468933.jpg","title":"平等公正的对待你和他的爱情，脚踩很多船最终会翻掉。 相关链接：林志颖删林心如微博无水印高清美女图片 腾讯微博首页","date":"2014-01-20","cmt":"","hot":"6"},{"src":"http://imglf1.ph.126.net/7JkA-H1p0o7Tao_qTKhVtQ==/3300575577009331327.jpg","title":"万一脆弱的不行了，请选好哭泣的对象，不要随便借肩膀和胸膛。相关链接：林志颖删林心如微博无水印高清美女图片 腾讯微博首页","date":"2014-01-20","cmt":"","hot":"6"},{"src":"http://imglf1.ph.126.net/tsLhrXYvNWLcL0QnYNkVqw==/1846475847321973759.jpg","title":"如果发短信息给你喜欢的人，他不回。不要再发。相关链接：林志颖删林心如微博无水印高清美女图片 腾讯微博首页","date":"2014-01-20","cmt":"","hot":"6"},{"src":"http://imglf2.ph.126.net/oD0ca6u4Mh5OVYqQb4gW6w==/6608261695515257960.jpg","title":"如果喜欢一个人，在允许的情况下，告诉对方。相关链接：林志颖删林心如微博无水印高清美女图片 腾讯微博首页","date":"2014-01-20","cmt":"","hot":"6"},{"src":"http://imglf1.ph.126.net/7cT3wwUEpcKcPE-cmLXV0Q==/6597637114658341027.jpg","title":"有固定的消遣场所，比如固定的咖啡馆、书店。让那个地方的服务生认识你，这样，你会在孤单时有个温暖的去处。相关链接：林志颖删林心如微博无水印高清美女图片 腾讯微博首页","date":"2014-01-20","cmt":"","hot":"3"},{"src":"http://imglf2.ph.126.net/9qSZlc2EioY5oR7y518uTQ==/2171016495469585601.jpg","title":"如果一个男人对你说他喜欢你，相信他。如果他说不再爱你，也相信他。任何时候，要告诉自己，一个不爱你的人离开，是幸运。 相关链接：林志颖删林心如微博无水印高清美女图片 腾讯微博首页","date":"2014-01-20","cmt":"","hot":"5"},{"src":"http://imglf0.ph.126.net/kxa2LrhkQWBP8wqBM-xWWQ==/6597997754472254340.jpg","title":"闲情时候自己煮花茶喝或者做茶点吃，放一段柔情音乐，翻阅几页好书，然后睡个懒觉，相关链接：林志颖删林心如微博无水印高清美女图片 腾讯微博首页快哉。 ","date":"2014-01-20","cmt":"","hot":"5"},{"src":"http://imglf0.ph.126.net/ymP0dxpSrJPMVyk8tyaDbw==/4939322891418719685.jpg","title":"不必为某个人选择销毁ID或者失踪。爱和不爱都将继续生活，结束就好好结束，何必苦了自己？ 相关链接：林志颖删林心如微博无水印高清美女图片 腾讯微博首页","date":"2014-01-20","cmt":"","hot":"6"},{"src":"http://imglf0.ph.126.net/XhLOqoXROpPubkiSIS7Xdg==/2107684625709507852.jpg","title":"你可以去爱一个男人，但是不要把自己的全部都赔进去。没有男人值得你用生命去讨好。你若不爱自己，怎么能让别人爱你？相关链接： 娄艺潇微博  zhou微博  qq微博","date":"2014-01-20","cmt":"","hot":""}]