[{"src":"http://imglf0.nosdn.127.net/img/ZXI5czR6SXRCTXE1VmRWRmJEOWxtOUp5VjNsSGFFUnExcm5BOVQyQm55dkZuVGVCZWxMalVBPT0.jpg?imageView&thumbnail=500x0&quality=96&stripmeta=0&type=jpg","title":"诱惑，美腿，美女来源：@小雨点9132","date":"2015-12-11","cmt":"","hot":"10"},{"src":"http://imglf1.nosdn.127.net/img/RWZWM2ZpK3Zjc2wxTmxJRGU4NnR4MlpqR21WdkVRN0prTitGWmhpYW5IdjlXM1RQVWpOcW5RPT0.jpg?imageView&thumbnail=500x0&quality=96&stripmeta=0&type=jpg","title":"小湿妹来源：白马啸西风","date":"2015-12-11","cmt":"","hot":"30"},{"src":"http://imglf.nosdn.127.net/img/b3BEc0ZwMHJiRE9KMHpHdE1ZYk9zSS96K3M2cjVmZjNWalN4QStDa2JHNWoyZE5Od29ac0RRPT0.jpg?imageView&thumbnail=500x0&quality=96&stripmeta=0&type=jpg","title":"来源：Fly tiger","date":"2015-12-11","cmt":"","hot":"110"},{"src":"http://imglf2.nosdn.127.net/img/b3BEc0ZwMHJiRE9KMHpHdE1ZYk9zRFFWWWpRRkszOExXTDRUSWhkYUgyVEs0VlpPbUoxcXhnPT0.jpg?imageView&thumbnail=500x0&quality=96&stripmeta=0&type=jpg","title":"来源：Fly tiger","date":"2015-12-11","cmt":"","hot":"246"},{"src":"http://imglf0.ph.126.net/G7UkvARXSRaT1BHw_fm6EQ==/6631238190003722532.jpg","title":"","date":"2015-12-10","cmt":"","hot":"22"},{"src":"http://imglf1.ph.126.net/vMHBrim3x9-7omszxHBCnw==/6630757703422537297.jpg","title":"","date":"2015-12-10","cmt":"","hot":"15"},{"src":"http://imglf2.ph.126.net/veHLlz02NW4ttY23yCVLJg==/6630609269352779930.jpg","title":"","date":"2015-12-10","cmt":"1","hot":"36"},{"src":"http://imglf1.nosdn.127.net/img/cm5sbVlaaElOa2k3WUVzK1dWWHBiNmJERGhUKzJNSWVReG5RS2dWZi9ITG1MVUJaZUdaZm9BPT0.jpg?imageView&thumbnail=500x0&quality=96&stripmeta=0&type=jpg","title":"艺术摄影","date":"2015-12-10","cmt":"","hot":"14"},{"src":"http://imglf0.nosdn.127.net/img/cm5sbVlaaElOa2cxSUtHdjlGa1BrU3lzVFltNk5ocGpnL3JaVFdlRGFsR1djazdhSU5kV2pRPT0.jpg?imageView&thumbnail=500x0&quality=96&stripmeta=0&type=jpg","title":"","date":"2015-12-10","cmt":"","hot":"18"},{"src":"http://imglf2.nosdn.127.net/img/bGl3bHlsa3pRZ2x5Mkcxb3hudmQ3UFRyNjNGRUZkQmI5TU8yUzhvd3JveTlIRW1tN3E2SE1BPT0.jpg?imageView&thumbnail=500x0&quality=96&stripmeta=0&type=jpg","title":"来源：丝露露","date":"2015-12-10","cmt":"","hot":"69"}]