[{"src":"http://imglf2.ph.126.net/RNkootEb92wUn6-19S8nJA==/4822510776083867168.jpg","title":"Mandy","date":"2014-04-23","cmt":"","hot":"34"},{"src":"http://imglf2.ph.126.net/p3PmFeNdyD3XD4aBz_Dg0g==/1423418957326433459.jpg","title":"Mandy qiang","date":"2014-04-23","cmt":"","hot":"26"},{"src":"http://imglf1.ph.126.net/4tTY0gXU9IoS2PXQc_wmXw==/1859705171227655584.jpg","title":"Mandy 吊带","date":"2014-04-23","cmt":"","hot":"50"},{"src":"http://imglf0.ph.126.net/roiJwDSvzCogXMQ14KYMFA==/6608238605771509398.jpg","title":"Mandy TUn","date":"2014-04-23","cmt":"","hot":"45"},{"src":"http://imglf1.ph.126.net/IoW52NYNA568nWN3Mj5BmQ==/6608420025190096939.jpg","title":"Mandy Luo","date":"2014-04-23","cmt":"","hot":"27"},{"src":"http://imglf1.ph.126.net/iAJJ5iL5kZfOph7bU0PjZg==/1422574532396301445.jpg","title":"Mandy luo","date":"2014-04-23","cmt":"","hot":"34"},{"src":"http://imglf2.ph.126.net/8xYjrAxibzAx169CvKbKtQ==/4794926228366429249.jpg","title":"Mandy Luo","date":"2014-04-23","cmt":"","hot":"40"},{"src":"http://imglf1.ph.126.net/jNSbwUnE_gRwf5yzhGQlyw==/1139692180802250160.jpg","title":"Mandy Luo","date":"2014-04-23","cmt":"","hot":"35"},{"src":"http://imglf1.ph.126.net/Io53hcAlcCGi3IjttudcWw==/6597938380844408422.jpg","title":"杨依 情趣","date":"2014-04-22","cmt":"","hot":"23"},{"src":"http://imglf2.ph.126.net/yEWUY8YkLdU7XfdQvVnpZA==/6597764658007224338.jpg","title":"杨依 luo","date":"2014-04-22","cmt":"","hot":"25"},{"src":"http://imglf1.ph.126.net/T9ljPixW5TSYhDA5KTLqOw==/4842776974407191800.jpg","title":"杨依 胸诱","date":"2014-04-22","cmt":"1","hot":"50"},{"src":"http://imglf1.ph.126.net/yWcW-FLmKx4YxwaZAsD3pA==/200691658494912520.jpg","title":"杨依 珠帘","date":"2014-04-22","cmt":"","hot":"34"},{"src":"http://imglf1.ph.126.net/gDU_Qn0wyw9-PsJEBNjT8w==/1606377692188040815.jpg","title":"杨依 情趣","date":"2014-04-22","cmt":"1","hot":"16"},{"src":"http://imglf2.ph.126.net/stjHbL-ZyTP_AfSe5F0AsQ==/2853874788970134257.jpg","title":"杨依 趣","date":"2014-04-22","cmt":"","hot":"31"},{"src":"http://imglf2.ph.126.net/NRG3WlsU-qY2aKzZa9gMLA==/6597948276449058326.jpg","title":"杨依 情趣","date":"2014-04-22","cmt":"1","hot":"37"},{"src":"http://imglf1.ph.126.net/Vy5IhZJx89d2Qfm9cWWTzA==/4815192426689343106.jpg","title":"林夕 床思","date":"2014-04-21","cmt":"1","hot":"33"},{"src":"http://imglf0.ph.126.net/JPWI9wAOwc5zOd7xKd1hNw==/2098677426454817871.jpg","title":"林夕 纱","date":"2014-04-21","cmt":"","hot":"39"},{"src":"http://imglf0.ph.126.net/sbbYRnHmGfapb_Elit8bBQ==/6597288569472201771.jpg","title":"林夕 美人鱼","date":"2014-04-21","cmt":"","hot":"28"},{"src":"http://imglf0.ph.126.net/gI4eIzpTfpKMuvRnfrA7Lw==/2184245819375003328.jpg","title":"林夕 美人鱼","date":"2014-04-21","cmt":"","hot":"25"},{"src":"http://imglf1.ph.126.net/q2cxy80nO5ixG8_awUTruA==/2041538006182698886.jpg","title":"林夕 美人鱼","date":"2014-04-21","cmt":"","hot":"36"},{"src":"http://imglf0.ph.126.net/Oi9gMRJyMwijGLOESgJO5Q==/3223451433390709620.jpg","title":"林夕 生活照","date":"2014-04-21","cmt":"1","hot":"31"},{"src":"http://imglf1.ph.126.net/DN-o_4k0r8nXkLULlmofgA==/2028590157254166493.jpg","title":"早安，泰迪熊","date":"2014-04-20","cmt":"","hot":"41"},{"src":"http://imglf2.ph.126.net/OKLYrTzOHBiR_NFfAFaDBQ==/6598249542635009198.jpg","title":"心之股","date":"2014-04-20","cmt":"","hot":"11"},{"src":"http://imglf0.ph.126.net/qOkBuBZJdV7UkygsZtSoEw==/6599299576238118246.jpg","title":"于大小姐 一叶遮胸","date":"2014-04-18","cmt":"","hot":"52"},{"src":"http://imglf1.ph.126.net/aaq1Ll01snH1GTFZ7KNPpw==/1821143099418230536.jpg","title":"于大小姐 M","date":"2014-04-18","cmt":"","hot":"36"},{"src":"http://imglf1.ph.126.net/LxpRETiGRUlPeIBCHutzyw==/3179822812000604908.jpg","title":"于大小姐 浴","date":"2014-04-18","cmt":"","hot":"32"},{"src":"http://imglf1.ph.126.net/G5v-RAtbosvGl2PEm6ncyw==/3026137474716548230.jpg","title":"于大小姐 泳装","date":"2014-04-18","cmt":"","hot":"65"},{"src":"http://imglf0.ph.126.net/uTutzhZsYSPQbABlolAQ6A==/2211267417139682661.jpg","title":"于大小姐 泳装","date":"2014-04-18","cmt":"","hot":"22"},{"src":"http://imglf2.ph.126.net/hjw_eLIpZn66S7rpSCMrYQ==/6608178132631923908.jpg","title":"晓伊 luo","date":"2014-04-16","cmt":"","hot":"25"},{"src":"http://imglf0.ph.126.net/mK1BBP4ETEy-bfxH72nynQ==/2677671453548662899.jpg","title":"晓伊 luo秀","date":"2014-04-16","cmt":"","hot":"15"}]